pyttsgen/__init__.py
pyttsgen/app.py
pyttsgen/cli.py
pyttsgen/config.py
pyttsgen/engine.py
pyttsgen/utils.py
pyttsgen-0.1.3.dist-info/LICENSE
pyttsgen-0.1.3.dist-info/METADATA
pyttsgen-0.1.3.dist-info/WHEEL
pyttsgen-0.1.3.dist-info/entry_points.txt
pyttsgen-0.1.3.dist-info/top_level.txt
pyttsgen-0.1.3.dist-info/RECORD
