Metadata-Version: 2.1
Name: pyttsgen
Version: 0.1.3
Summary: A developer-friendly, plug-and-play TTS library for Python
Author: RePromptsQuest
Author-email: repromptsquest@gmail.com
Classifier: Programming Language :: Python :: 3
Classifier: Operating System :: OS Independent
License-File: LICENSE
Requires-Dist: edge-tts
Requires-Dist: streamlit
Requires-Dist: nest-asyncio
